dlframe/CalculationNode.py
dlframe/CalculationNodeManager.py
dlframe/ExecutionNode.py
dlframe/Logger.py
dlframe/RecursiveWarpper.py
dlframe/TimeWarpper.py
dlframe/WebManager.py
dlframe/__init__.py
dlframe/cs_manager/CSManager.py
dlframe/cs_manager/Client.py
dlframe/cs_manager/LinkSender.py
dlframe/cs_manager/ModuleSender.py
dlframe/cs_manager/Pkt.py
dlframe/cs_manager/Server.py
dlframe/cs_manager/__init__.py
dlframe/cs_manager/consts.py
dlframe/cs_manager/utils.py
dynamic_links-0.2.2.dist-info/METADATA
dynamic_links-0.2.2.dist-info/WHEEL
dynamic_links-0.2.2.dist-info/top_level.txt
dynamic_links-0.2.2.dist-info/RECORD
