Metadata-Version: 2.1
Name: dynamic-links
Version: 0.2.2
Summary: a calculation framework
Home-page: https://github.com/picpic2013/dlframe-back
Author: PIC
Author-email: picpic2019@gmail.com
License: MIT
Requires-Python: >=3.10, <4
Requires-Dist: websockets (>=10.3)
Requires-Dist: numpy
Requires-Dist: Pillow
